transaction_report/__main__.py
transaction_report/transaction_report.py
transaction_report_bertollo-0.1.0.dist-info/METADATA
transaction_report_bertollo-0.1.0.dist-info/WHEEL
transaction_report_bertollo-0.1.0.dist-info/entry_points.txt
transaction_report_bertollo-0.1.0.dist-info/top_level.txt
transaction_report_bertollo-0.1.0.dist-info/RECORD
