Metadata-Version: 2.1
Name: transaction_report_bertollo
Version: 0.1.0
Summary: A package to generate transaction reports from CSV files.
Author-email: Victor Bertollo <bertollo.victor@gmail.com>
Requires-Dist: pandas
